pamda/__init__.py
pamda/pamda.py
pamda/pamda_curry.py
pamda/pamda_fast.py
pamda/pamda_timer.py
pamda/pamda_utils.py
pamda/pamda_wrappers.py
pamda-2.9.0.dist-info/licenses/LICENSE
pamda-2.9.0.dist-info/METADATA
pamda-2.9.0.dist-info/WHEEL
pamda-2.9.0.dist-info/top_level.txt
pamda-2.9.0.dist-info/RECORD
