Metadata-Version: 2.4
Name: pamda
Version: 2.9.0
Summary: Functional programming for python
Author-email: Connor Makowski <conmak@mit.edu>
Project-URL: Homepage, https://github.com/connor-makowski/pamda
Project-URL: Bug Tracker, https://github.com/connor-makowski/pamda/issues
Project-URL: Documentation, https://connor-makowski.github.io/pamda/pamda/pamda.html
Classifier: Programming Language :: Python :: 3
Classifier: License :: OSI Approved :: MIT License
Classifier: Operating System :: OS Independent
Requires-Python: >=3.11
License-File: LICENSE
Requires-Dist: type_enforced<3.0.0,>=2.1.0
Dynamic: license-file
